CHANGELOG.md
MANIFEST.in
README.md
setup.cfg
setup.py
versioneer.py
src/libreflow/__init__.py
src/libreflow.extensions.anpo.texture_proxies.egg-info/PKG-INFO
src/libreflow.extensions.anpo.texture_proxies.egg-info/SOURCES.txt
src/libreflow.extensions.anpo.texture_proxies.egg-info/dependency_links.txt
src/libreflow.extensions.anpo.texture_proxies.egg-info/top_level.txt
src/libreflow/extensions/__init__.py
src/libreflow/extensions/anpo/__init__.py
src/libreflow/extensions/anpo/texture_proxies/__init__.py
src/libreflow/extensions/anpo/texture_proxies/_version.py
src/libreflow/extensions/anpo/texture_proxies/create_proxies.py
src/libreflow/extensions/anpo/texture_proxies/get_max_width.py